dictys/__init__.py
dictys/__main__.py
dictys/chromatin.py
dictys/dynamic.py
dictys/network.py
dictys/preproc.py
dictys/traj.py
dictys/net/__init__.py
dictys/net/layout.py
dictys/net/stat.py
dictys/plot/__init__.py
dictys/plot/dynamic.py
dictys/plot/layout.py
dictys/plot/panel.py
dictys/plot/static.py
dictys/scripts/chromatin_homer.py
dictys/scripts/chromatin_homer.sh
dictys/scripts/chromatin_macs2.sh
dictys/scripts/chromatin_wellington.sh
dictys/scripts/helper/expression.py
dictys/scripts/helper/expression_mtx.py
dictys/scripts/helper/fetch_osf.sh
dictys/scripts/helper/gene_gtf.sh
dictys/scripts/helper/genome_homer.sh
dictys/scripts/helper/makefile_check.py
dictys/scripts/helper/makefile_template.sh
dictys/scripts/helper/makefile_update.py
dictys/scripts/helper/motif_homer.sh
dictys/scripts/helper/network_inference.sh
dictys/scripts/helper/repo_dataverse.py
dictys/scripts/helper/repo_zenodo.py
dictys/scripts/helper/repodown.sh
dictys/scripts/helper/split_bam.sh
dictys/scripts/helper/split_bam_text.py
dictys/scripts/makefiles/common.mk
dictys/scripts/makefiles/config.mk
dictys/scripts/makefiles/dynamic.mk
dictys/scripts/makefiles/env_none.mk
dictys/scripts/makefiles/env_singularity.mk
dictys/scripts/makefiles/static.mk
dictys/scripts/makefiles/test_dynamic.mk
dictys/scripts/makefiles/test_static.mk
dictys/utils/__init__.py
dictys/utils/file.py
dictys/utils/importing.py
dictys/utils/networkx.py
dictys/utils/numpy.py
dictys/utils/parallel.py
dictys/utils/shell.py
dictys-1.1.0.data/scripts/dictys
dictys-1.1.0.data/scripts/dictys_helper
docstring2argparse/__init__.py
dictys-1.1.0.dist-info/LICENSE
dictys-1.1.0.dist-info/METADATA
dictys-1.1.0.dist-info/WHEEL
dictys-1.1.0.dist-info/top_level.txt
dictys-1.1.0.dist-info/RECORD
