Metadata-Version: 2.1
Name: dictys
Version: 1.1.0
Summary: Context specific and dynamic gene regulatory network reconstruction and analysis
Home-page: https://github.com/pinellolab/dictys
Author: Lingfei Wang, Nikolaos Trasanidis, Luca Pinello
Author-email: Lingfei.Wang.github@outlook.com, ntrasanidis@mgh.harvard.edu, lpinello@mgh.harvard.edu
Classifier: Development Status :: 5 - Production/Stable
Classifier: Environment :: Console
Classifier: Environment :: GPU :: NVIDIA CUDA :: 11.3
Classifier: Environment :: GPU :: NVIDIA CUDA :: 11.6
Classifier: Environment :: GPU :: NVIDIA CUDA :: 11.7
Classifier: Framework :: Jupyter
Classifier: Framework :: Matplotlib
Classifier: Intended Audience :: Developers
Classifier: Intended Audience :: End Users/Desktop
Classifier: Intended Audience :: Science/Research
Classifier: License :: OSI Approved :: GNU Affero General Public License v3
Classifier: Operating System :: OS Independent
Classifier: Programming Language :: Python :: 3.9
Classifier: Programming Language :: Python :: 3.10
Classifier: Topic :: Scientific/Engineering :: Bio-Informatics
Classifier: Topic :: Scientific/Engineering :: Visualization
Requires-Python: >=3.9
License-File: LICENSE
Requires-Dist: numpy
Requires-Dist: pandas
Requires-Dist: docutils
Requires-Dist: h5py
Requires-Dist: pyro-ppl
Requires-Dist: scipy
Requires-Dist: networkx
Requires-Dist: pybedtools
Requires-Dist: pyDNase
Requires-Dist: threadpoolctl
Requires-Dist: joblib
Requires-Dist: torch
Requires-Dist: matplotlib
Requires-Dist: adjustText
Requires-Dist: jupyter
